neural_booster/__init__.py
neural_booster/gru.py
neural_booster/libneural_booster.so
neural_booster/lstm.py
neural_booster/nb.py
neural_booster-0.0.5.dist-info/LICENSE
neural_booster-0.0.5.dist-info/METADATA
neural_booster-0.0.5.dist-info/WHEEL
neural_booster-0.0.5.dist-info/top_level.txt
neural_booster-0.0.5.dist-info/RECORD
