Metadata-Version: 2.1
Name: neural-booster
Version: 0.0.5
Summary: Neural Booster targeting to boost inference performance.
Home-page: https://github.com/neural-booster/neural_booster
Author: Neural Booster
Author-email: neural_booster@163.com
License: Apache 2.0
Keywords: inference,machine learning,x86,x86_64,avx512,neural network,
Platform: x86_64
Requires-Python: >=3.6
License-File: LICENSE
